MANIFEST.in
README.md
gofedlib-cli
requirements.txt
setup.cfg
setup.py
gofedlib/__init__.py
gofedlib/types.py
gofedlib/utils.py
gofedlib.egg-info/PKG-INFO
gofedlib.egg-info/SOURCES.txt
gofedlib.egg-info/dependency_links.txt
gofedlib.egg-info/requires.txt
gofedlib.egg-info/top_level.txt
gofedlib/config/__init__.py
gofedlib/config/config.py
gofedlib/config/lib.conf
gofedlib/config/libconfig.py
gofedlib/distribution/__init__.py
gofedlib/distribution/distributionnameparser.py
gofedlib/distribution/distributionsnapshot.py
gofedlib/distribution/helpers.py
gofedlib/distribution/packagemanager.py
gofedlib/distribution/packagenamegenerator.py
gofedlib/distribution/packagenamegeneratorbuilder.py
gofedlib/distribution/test_distributionnameparser.py
gofedlib/distribution/test_packagenamegenerator.py
gofedlib/distribution/clients/__init__.py
gofedlib/distribution/clients/bodhi/__init__.py
gofedlib/distribution/clients/bodhi/client.py
gofedlib/distribution/clients/fakedata/data.json
gofedlib/distribution/clients/koji/__init__.py
gofedlib/distribution/clients/koji/client.py
gofedlib/distribution/clients/koji/fakeclient.py
gofedlib/distribution/clients/koji/test_client.py
gofedlib/distribution/clients/pkgdb/__init__.py
gofedlib/distribution/clients/pkgdb/client.py
gofedlib/distribution/clients/pkgdb/fakeclient.py
gofedlib/distribution/clients/pkgdb/fakedata.json
gofedlib/distribution/clients/pkgdb/test_client.py
gofedlib/distribution/data/ip2package_mapping.json
gofedlib/distribution/eco/__init__.py
gofedlib/distribution/eco/capturer.py
gofedlib/docs/proposal.md
gofedlib/docs/providers.md
gofedlib/go/__init__.py
gofedlib/go/contentmetadataextractor.py
gofedlib/go/data2specmodeldata.py
gofedlib/go/functions.py
gofedlib/go/projectinfo.py
gofedlib/go/projectinfobuilder.py
gofedlib/go/snapshot.py
gofedlib/go/apidiff/__init__.py
gofedlib/go/apidiff/apidiff.py
gofedlib/go/apidiff/test_apidiff.py
gofedlib/go/apidiff/testdata/api1.json
gofedlib/go/apidiff/testdata/api2.json
gofedlib/go/importpath/__init__.py
gofedlib/go/importpath/decomposer.py
gofedlib/go/importpath/decomposerbuilder.py
gofedlib/go/importpath/normalizer.py
