Metadata-Version: 1.0
Name: gofedlib
Version: 0.1.0
Summary: A set of python modules carrying operation related to Go source codes analysis used in Gofed
Home-page: https://github.com/gofed/gofedlib
Author: Jan Chaloupka
Author-email: jchaloup@redhat.com
License: GPL
Keywords: gofed golang API dependencies
Platform: UNKNOWN
